augllm/__init__.py
augllm/augmented_llm.py
augllm/function_calling.py
augllm/image_controller.py
augllm/llm_interface.py
augllm/make_image_paths.py
augllm/prompt_builder.py
augllm/tool.py
augllm/tool_handler.py
test/__init__.py
test/test_chat.py
test/test_image.py
augllm-1.1.dist-info/LICENSE
augllm-1.1.dist-info/METADATA
augllm-1.1.dist-info/WHEEL
augllm-1.1.dist-info/top_level.txt
augllm-1.1.dist-info/RECORD
