Metadata-Version: 2.1
Name: augllm
Version: 1.1
Summary: ('A library for augmenting large language models',)
Home-page: https://github.com/ToPo-ToPo-ToPo/augllm
Author: Shun Ogawa (a.k.a. "ToPo")
License: Apache License Version 2.0
Classifier: Programming Language :: Python :: 3
Classifier: License :: OSI Approved :: Apache Software License
Requires-Python: >=3.11
License-File: LICENSE
Requires-Dist: pyyaml
Requires-Dist: ollama
Requires-Dist: PyMuPDF
Requires-Dist: Pillow
Requires-Dist: tqdm
Requires-Dist: pytest
